seculint/__init__.py
seculint/ai_integration.py
seculint/cli.py
seculint/git_utils.py
seculint/ignore.py
seculint/models.py
seculint/patterns.py
seculint/reporting.py
seculint/scanner.py
seculint/seculintignore
seculint-0.3.1.dist-info/entry_points.txt
seculint-0.3.1.dist-info/METADATA
seculint-0.3.1.dist-info/WHEEL
seculint-0.3.1.dist-info/RECORD
