Metadata-Version: 2.4
Name: seculint
Version: 0.3.1
Summary: Local secret & privacy leak scanner with optional AI verification
License: MIT
Keywords: security,secrets,scanner,lint,ai,devsecops
Author: Shahid Riaz Bhatti
Author-email: shahid.bhatti@hotmail.com
Requires-Python: >=3.10
Classifier: Programming Language :: Python :: 3
Classifier: License :: OSI Approved :: MIT License
Classifier: Operating System :: OS Independent
Classifier: Development Status :: 4 - Beta
Classifier: Intended Audience :: Developers
Classifier: Topic :: Security
Classifier: Environment :: Console
Requires-Dist: openai (>=2.8.1,<3.0.0)
Requires-Dist: setuptools (>=80.9.0,<81.0.0)
Requires-Dist: wheel (>=0.45.1,<0.46.0)
